src/__init__.py
src/cli.py
src/command.py
src/config.py
src/formatters.py
src/server.py
src/tools.py
mseep_dbt_cli_mcp-0.1.4.dist-info/METADATA
mseep_dbt_cli_mcp-0.1.4.dist-info/WHEEL
mseep_dbt_cli_mcp-0.1.4.dist-info/entry_points.txt
mseep_dbt_cli_mcp-0.1.4.dist-info/licenses/LICENSE
mseep_dbt_cli_mcp-0.1.4.dist-info/RECORD
